.coveragerc
CHANGELOG.rst
MANIFEST.in
README.rst
VERSION
requirements-test.txt
requirements.txt
setup.cfg
setup.py
guillotina_nats/__init__.py
guillotina_nats/interfaces.py
guillotina_nats/models.py
guillotina_nats/utility.py
guillotina_nats.egg-info/PKG-INFO
guillotina_nats.egg-info/SOURCES.txt
guillotina_nats.egg-info/dependency_links.txt
guillotina_nats.egg-info/requires.txt
guillotina_nats.egg-info/top_level.txt
guillotina_nats.egg-info/zip-safe
guillotina_nats/tests/__init__.py
guillotina_nats/tests/conftest.py
guillotina_nats/tests/fixtures.py
guillotina_nats/tests/test_connection.py
guillotina_nats/tests/test_jetstream.py
guillotina_nats/tests/test_pubsub.py
guillotina_nats/tests/test_stream.py
guillotina_nats/tests/utils.py