Metadata-Version: 1.1
Name: guillotina-nats
Version: 1.0.3
Summary: UNKNOWN
Home-page: https://github.com/guillotinaweb/guillotina_nats
Author: Ramon Navarro Bosch
Author-email: ramon@flaps.io
License: BSD
Platform: UNKNOWN
Classifier: Development Status :: 4 - Beta
Classifier: Programming Language :: Python :: 3.7
Classifier: Topic :: Software Development :: Libraries :: Python Modules
